[
  {
    "name": "Jae-Hyeon Pyeon",
    "research_interests": ["High-performance DPLL"],
    "tape_out_schedule": [
      {
        "date": "2024.07",
        "process": "28-nm S"
      },
      {
        "date": "2024.09",
        "process": "40-nm T"
      },
      {
        "date": "2025.07",
        "process": "28-nm S"
      }
    ],
    "education": [
    "B.S., Department of Electrical Engineering, Hanyang University, Ansan, Korea (2018.03 ~ 2024.08)"
    ],
    "publication": ["ICEIC'25"],
    "Awards": ["ISOCC'25 Chip Design Contest"],
    "biography": "Received a B.S. degree in the school of electrical engineering at Hanyang University, Ansan, South Korea. His research interests include analog and digital circuit designs of phase-locked-loop (PLL).",
    "email": "ccomo7004@hanyang.ac.kr",
    "profile_img": "img/jh-pyeon-profile-img.png",
    "position": ""
  },
  {
    "name": "So-Yeon Kwon",
    "education": [
    "B.S., Department of Electrical Engineering, Hanyang University, Ansan, Korea (2019.03 ~ 2025.02)"
    ],
    "research_interests": ["Digital PIM"],
    "tape_out_schedule": [
      {
        "date": "2024",
        "process": ""
      }
    ],
    "Awards": [],
    "biography": "Received a B.S. degree in the school of Applied Physics at Hanyang University, Ansan, South Korea. She is currently pursuing a M.S. degree in the school of electrical engineering at Hanyang University, Ansan, South Korea. Her research interests include artificial intelligence hardware design and processing in memory (PIM).",
    "email": "sykwon00@hanyang.ac.kr",
    "profile_img": "img/sw-kwon-profile-image.jpeg",
    "position": ""
  },
  {
    "name": "In-Ho Han",
    "research_interests": ["PLL"],
    "tape_out_schedule": [
      {
        "date": "2025.07",
        "process": "28-nm S"
      }
    ],
    "education": [
    "B.S., Department of Electronic Engineering, Gachon University, Seoungnam, Korea (2017.03 ~ 2023.02)"
    ],
    "experience": [
    "FAE(Field Application Engineer), Dongwoon Anatech, Seoul, Korea (2023.04 ~ 2024.08 )"
    ],    
    "publication": ["ICEIC'25"],
    "biography": "Received a B.S. degree in electrical engineering from Gachon University, Sungnam, South Korea. He is currently pursuing a M.S. degree in the school of electrical engineering at Hanyang University, Ansan, South Korea. His research interests include analog and digital circuit designs of phase-locked-loop (PLL).",
    "email": "inho0303@hanyang.ac.kr",
    "profile_img": "img/ih-han-profile-img.jpg",
    "position": "",
    "cv": "https://drive.google.com/file/d/1YalveNStnhNMOz_vrlERhe6yrfSEJqPg/view?usp=drive_link"
  },
  {
    "name": "Seung-Hwan Gong",
    "research_interests": ["CDR, DSP-based Receiver"],
    "tape_out_schedule": [
      {
        "date": "2025.02",
        "process": "28-nm T"
      }
    ],
    "education": [
    "B.S., Department of Electronics Engineering, Kangwon National University, Chuncheon, Korea (2018.03 ~ 2024.02)"
    ],
    "publication": ["JSSC'25 <a href='https://ieeexplore.ieee.org/document/11029275' target='_blank' rel='noopener noreferrer' class='news-link'>[Paper]</a>"],
    "Awards": ["ISOCC'25 best paper award", "ISOCC'25 Chip Design Contest", "2025 IEEE Seoul Section Student Paper Bronze Award"],
    "biography": "Received a B.S. degree in the school of electrical engineering at Gangwon University, Ansan, South Korea. He is currently pursuing a M.S. degree in the school of electrical engineering at Hanyang University, Ansan, South Korea. His research interests include CDR, DSP-based Receiver.",
    "email": "fire051324@gmail.com",
    "profile_img": "img/sh-gong-profile-image.jpg",
    "position": ""
  },
  {
    "name": "Dong-Ho Kim",
    "research_interests": ["DSP-based Transmitter"],
    "tape_out_schedule": [
      {
        "date": "2025.09",
        "process": "28-nm T"
      }
    ],
    "education": [
    "B.S., Department of Electrical Engineering, Hanyang University, Ansan, Korea (2017.03 ~ 2023.08)"
    ],
    "publication": ["ASSCC'25 <a href='https://ieeexplore.ieee.org/document/11349396' target='_blank' rel='noopener noreferrer' class='news-link'>[Paper]</a>"],
    "Awards": ["제 26회 대한민국 반도체설계대전 특허청장상 수상", "2025 IEEE Seoul Section Student Paper Bronze Award"],
    "biography": "Received a B.S. degree in the school of electrical engineering at Hanyang University, Ansan, South Korea. He is currently pursuing a M.S. degree in the school of electrical engineering at Hanyang University, Ansan, South Korea. His research interests include DSP-DAC based transmitter.",
    "email": "dpdl112@hanyang.ac.kr",
    "profile_img": "img/dh-kim-profile-image.jpg",
    "position": "",
    "cv": "https://drive.google.com/file/d/1IIwGJfwAkVuCNuxvlFhy0Qp3Lv7o2et1/view?usp=drive_link"
  },
  {
    "name": "Jae-Geon Lee",
    "research_interests": ["DSP-based Receiver"],
    "tape_out_schedule": [
      {
        "date": "2024.09",
        "process": "40-nm T"
      },
      {
        "date": "2025.07",
        "process": "28-nm T"
      }
    ],
    "education": [
    "B.S., Department of Electrical Engineering, Hanyang University, Ansan, Korea (2019.03 ~ 2025.02)"
    ],
    "publication": [
    "ICEIC'24 <a href='https://ieeexplore.ieee.org/document/10457160' target='_blank' rel='noopener noreferrer' class='news-link'>[Paper]</a>",
    "ASSCC'24[JSSC invited] <a href='https://ieeexplore.ieee.org/document/10848602' target='_blank' rel='noopener noreferrer' class='news-link'>[Paper]</a>",
    "JSSC'25 <a href='https://ieeexplore.ieee.org/document/11029275' target='_blank' rel='noopener noreferrer' class='news-link'>[Paper]</a>",
    "ITC-CSCC '25 <a href='https://ieeexplore.ieee.org/document/11137667' target='_blank' rel='noopener noreferrer' class='news-link'>[Paper]</a>",
    "ASSCC'25 <a href='https://ieeexplore.ieee.org/document/11349558' target='_blank' rel='noopener noreferrer' class='news-link'>[Paper]</a>"],
    "Awards": ["석사과정생 연구장려금 '25-2 - '26-1 [NRF]", "2025 IEEE Seoul Section Student Paper Bronze Award", "2025 한양대학교 BK21 우수논문상"],
    "biography": "Received a B.S. degree in the school of electrical engineering at Hanyang University, Ansan, South Korea. He is currently pursuing a M.S. degree in the school of electrical engineering at Hanyang University, Ansan, South Korea. His research interests include Clock and data recovery (CDR) and DSP-based Receiver.",
    "email": "dlworjs@hanyang.ac.kr",
    "profile_img": "img/jg-lee-profile-img.jpeg",
    "position": "Server Manager",
    "cv": "https://drive.google.com/file/d/12ue5Z6KN3z0orGQJY3S3WTa_Z84VX9Mh/view?usp=sharing"
  },
  {
    "name": "Seung-Mo Jin",
    "research_interests": ["DSP-based Transmitter"],
    "tape_out_schedule": [
      {
        "date": "2025.09",
        "process": "28-nm T"
      }
    ],
    "education": [
    "B.S., Department of Electrical Engineering, Hanyang University, Ansan, Korea (2019.03 ~ 2025.02)"
    ],
    "publication": [
      "ICEIC'24 <a href='https://ieeexplore.ieee.org/document/10457226' target='_blank' rel='noopener noreferrer' class='news-link'>[Paper]</a>", 
      "ISOCC'2024 <a href='https://ieeexplore.ieee.org/document/10762215' target='_blank' rel='noopener noreferrer' class='news-link'>[Paper]</a>", 
      "ASSCC'25 <a href='https://ieeexplore.ieee.org/document/11349396' target='_blank' rel='noopener noreferrer' class='news-link'>[Paper]</a>"
    ],
    "Awards": ["2023-2 SCCUD 구두 발표 최우수상", "2024.05. SOC 학술대회 우수발표 논문상", "2024-1 SCCuD DAY 구두 발표 최우수상", "2024-1 공학대학 켑스톤 페어 동상", "2024-2 SCCuD DAY 구두 발표 대상", "석사과정생 연구장려금 '25-2 - '26-1 [NRF]", "제 26회 대한민국 반도체설계대전 특허청장상 수상", "ISOCC'25 best paper award", "2025 IEEE Seoul Section Student Paper Bronze Award"],
    "biography": "Received a B.S. degree in the school of electrical engineering at Hanyang University, Ansan, South Korea. He is currently pursuing a M.S. degree in the school of electrical engineering at Hanyang University, Ansan, South Korea. His research interests include DSP-DAC based transmitter.",
    "email": "victorymo@hanyang.ac.kr",
    "profile_img": "img/sm-jin-profile-img.jpg",
    "position": "Lab Captain",
    "cv": "https://drive.google.com/file/d/1Eft6w9CcVNDBiUG3iebRLbt_Zigzns70/view?usp=drive_link"
  },
  {
  "name": "Hyeon-Seo Kim",
  "research_interests": ["Analog Digital Converter (ADC)"],
  "Awards": [],
  "biography": "Received a B.S. degree in the school of electrical engineering at Hanyang University, Ansan, South Korea. He is currently pursuing a M.S. degree in the school of electrical engineering at Hanyang University, Ansan, South Korea. His research interests include analog digital converter (ADC)",
  "email": "hyeonseo1833@gmail.com",
  "profile_img": "img/sh-kim2-profile-image.png",
  "position": ""
},
{
  "name": "Seol-Hyeon Kim",
  "research_interests": ["AI hardware design and PIM"],
  "Awards": [],
  "biography": "Received a B.S. degree in the school of system semiconductor enginerring at Sangmyung University, Cheonan, South Korea. She is currently pursuing a M.S. degree in the school of electrical engineering at Hanyang University, Ansan, South Korea. Her research interests include artificial intelligence hardware design and processing in memory (PIM).",
  "email": "congcongsister@naver.com",
  "profile_img": "img/sh-kim-profile-image.jpg",
  "position": ""
},
{
    "name": "Dong-Eon Jin",
    "research_interests": ["Analog Digital Converter (ADC)"],
    "education": [
    "B.S., Department of Electrical Engineering, Hanyang University, Ansan, Korea (2019.03 ~ 2025.02)"
    ],
    "Awards": [],
    "biography": "Received a B.S. degree in the school of electrical engineering at Hanyang University, Ansan, South Korea. He is currently pursuing a M.S. degree in the school of electrical engineering at Hanyang University, Ansan, South Korea. His research interests include analog digital converter (ADC).",
    "email": "dujin0509@hanyang.ac.kr",
    "profile_img": "img/de-jin-profile-image.jpg",
    "position": ""
},
{
    "name": "Joon-Seok Kwon",
    "research_interests": ["Wireline Interface"],
    "education": [
    "B.S., Department of Electrical Engineering, Hanyang University, Ansan, Korea (2017.03 ~ 2023.02)"
    ],
    "experience": [
    "Engineer, IP Development Team, FINECHIPS INC., Yongin-si, Gyeonggi-do, Korea (2023.01 ~ 2025.06 )"
    ],
    "Awards": [],
    "biography": "Received a B.S. degree in the school of electrical engineering at Hanyang University, Ansan, South Korea. He is currently pursuing a M.S. degree in the school of electrical engineering at Hanyang University, Ansan, South Korea. His research interests include Wireline Interface.",
    "email": "qwe3016@hanyang.ac.kr",
    "profile_img": "img/js-kwon-profile-image.jpg",
    "position": ""
}
]
